wp_imazu/__init__.py
wp_imazu/client.py
wp_imazu/packet.py
wp_imazu-0.0.36.dist-info/LICENSE
wp_imazu-0.0.36.dist-info/METADATA
wp_imazu-0.0.36.dist-info/WHEEL
wp_imazu-0.0.36.dist-info/top_level.txt
wp_imazu-0.0.36.dist-info/RECORD
