Metadata-Version: 2.1
Name: wp-imazu
Version: 0.0.36
Summary: WallPad WpImazu
Home-page: https://gitlab.com/rs_wall_pad/wp_imazu
Author: stkang90
Author-email: stkang90@gmail.com
License: UNKNOWN
Project-URL: Bug Tracker, https://gitlab.com/rs_wall_pad/wp_imazu/-/issues
Platform: UNKNOWN
Classifier: Intended Audience :: Developers
Classifier: Programming Language :: Python :: 3
Classifier: License :: OSI Approved :: MIT License
Classifier: Operating System :: OS Independent
Requires-Python: >=3.8
License-File: LICENSE
Requires-Dist: wp-socket >=0.0.27
